dlt_source_google_workspace/__init__.py
dlt_source_google_workspace/api_client.py
dlt_source_google_workspace/tests/__init__.py
dlt_source_google_workspace/tests/test_noop.py
dlt_source_google_workspace-0.0.2.dist-info/METADATA
dlt_source_google_workspace-0.0.2.dist-info/WHEEL
dlt_source_google_workspace-0.0.2.dist-info/licenses/LICENSE
dlt_source_google_workspace-0.0.2.dist-info/RECORD
