Metadata-Version: 2.4
Name: dlt-source-google-workspace
Version: 0.0.2
Summary: DLT (dlthub.com) source for Google Workspace
Author: Planet A Ventures
Maintainer-email: Joscha Feth <joscha@planet-a.com>
License: MIT
License-File: LICENSE
Keywords: calendar,dlt,dlthub,google,workspace
Classifier: Development Status :: 4 - Beta
Classifier: Intended Audience :: Developers
Classifier: License :: OSI Approved :: MIT License
Classifier: Programming Language :: Python :: 3
Classifier: Programming Language :: Python :: 3.12
Classifier: Programming Language :: Python :: 3.13
Requires-Python: >=3.12
Requires-Dist: dlt>=1.9.0
Requires-Dist: google-api-python-client>=2.165.0
Requires-Dist: google-auth-oauthlib>=1.2.1
Provides-Extra: show
Requires-Dist: dlt[duckdb]>=1.9.0; extra == 'show'
Requires-Dist: streamlit>=1.41.1; extra == 'show'
Requires-Dist: watchdog>=6.0.0; extra == 'show'
